acl2_kernel/__init__.py
acl2_kernel/__main__.py
acl2_kernel/install.py
acl2_kernel/kernel.py
acl2_kernel-0.3.1.dist-info/LICENSE.md
acl2_kernel-0.3.1.dist-info/WHEEL
acl2_kernel-0.3.1.dist-info/METADATA
acl2_kernel-0.3.1.dist-info/RECORD
