Metadata-Version: 2.1
Name: acl2-kernel
Version: 0.3.1
Summary: Jupyter Kernel for ACL2
Home-page: https://github.com/tani/acl2-kernel
License: Apache-2.0
Author: TANIGUCHI Masaya
Author-email: m@docs.casa
Requires-Python: >=3.8,<4.0
Classifier: License :: OSI Approved :: Apache Software License
Classifier: Programming Language :: Python :: 3
Classifier: Programming Language :: Python :: 3.10
Classifier: Programming Language :: Python :: 3.8
Classifier: Programming Language :: Python :: 3.9
Requires-Dist: ipykernel (>=6.6.0,<7.0.0)
Requires-Dist: ipython (>=7.16.2,<8.0.0)
Requires-Dist: jupyter_client (>=6.1.3,<7.0.0)
Requires-Dist: pexpect (>=4.8.0,<5.0.0)
Requires-Dist: regex (>=2021.11.10,<2022.0.0)
Project-URL: Repository, https://github.com/tani/acl2-kernel.git
